{
  "ingestion": {
    "rateLimit": 50
  },
  "payers": [
    {
      "payer_id": "anthem",
      "name": "Aetna - Consistent 60s",
      "processing_delay_ms": {
        "min": 60000,
        "max": 60000
      },
      "adjudication_rules": {
        "payer_percentage": 0.8,
        "copay_fixed_amount": 25,
        "deductible_percentage": 0.1
      }
    },
    {
      "payer_id": "united_health_group",
      "name": "BCBS - Consistent 120s",
      "processing_delay_ms": {
        "min": 120000,
        "max": 120000
      },
      "adjudication_rules": {
        "payer_percentage": 0.75,
        "copay_fixed_amount": 30,
        "deductible_percentage": 0.15
      }
    },
    {
      "payer_id": "medicare",
      "name": "Cigna - Consistent 180s",
      "processing_delay_ms": {
        "min": 180000,
        "max": 180000
      },
      "adjudication_rules": {
        "payer_percentage": 0.82,
        "copay_fixed_amount": 20,
        "deductible_percentage": 0.12
      }
    }
  ],
  "postgres": {
    "clearinghouse": {
      "host": "localhost",
      "port": 5434,
      "username": "postgres",
      "password": "postgres",
      "database": "clearinghouse"
    },
    "billing": {
      "host": "localhost",
      "port": 5433,
      "username": "postgres",
      "password": "postgres",
      "database": "billing"
    }
  }
}